{
  "_disabled": "false",
  "host": "aarch64-Linux",
  "rank": "",
  "pkg": "xargs",
  "pkg_family": "findutils",
  "pkg_id": "pkgforge-cargo.findutils.stable",
  "pkg_name": "xargs",
  "pkg_type": "static",
  "pkg_webpage": "https://crates.io/crates/findutils",
  "bundle": "false",
  "category": [
    "Utility"
  ],
  "description": "Rust implementation of GNU findutils",
  "homepage": [
    "https://github.com/uutils/findutils"
  ],
  "license": [
    "MIT"
  ],
  "maintainer": [
    "pkgforge-cargo (https://github.com/pkgforge-cargo/builder)"
  ],
  "provides": [
    "find",
    "testing-commandline",
    "xargs"
  ],
  "note": [
    "[EXTERNAL] (This is an Official but externally maintained repository)",
    "This package was automatically built from crates.io using cargo-cross",
    "Provided by: https://github.com/pkgforge-cargo/builder",
    "Learn More: https://docs.pkgforge.dev/repositories/external/pkgforge-cargo"
  ],
  "src_url": "https://crates.io/api/v1/crates/findutils/0.8.0/download",
  "tag": [
    "Utility"
  ],
  "version": "0.8.0",
  "version_upstream": "0.8.0",
  "bsum": "7c3a2badcef7ce104ef688a329f518cfa0e8ceca0bff7a55df68f4f6226dce56",
  "build_date": "2025-06-14T07:45:33Z",
  "build_gha": "https://github.com/pkgforge-cargo/builder/actions/runs/15649544821",
  "build_id": "15649544821",
  "build_log": "https://api.ghcr.pkgforge.dev/pkgforge-cargo/findutils/stable/xargs?tag=0.8.0-aarch64-Linux&download=xargs.log",
  "deprecated": "false",
  "desktop_integration": "false",
  "download_count": "2063",
  "download_url": "https://api.ghcr.pkgforge.dev/pkgforge-cargo/findutils/stable/xargs?tag=0.8.0-aarch64-Linux&download=xargs",
  "external": "true",
  "ghcr_pkg": "ghcr.io/pkgforge-cargo/findutils/stable/xargs:0.8.0-aarch64-Linux",
  "ghcr_url": "https://ghcr.io/pkgforge-cargo/findutils/stable/xargs",
  "installable": "true",
  "manifest_url": "https://api.ghcr.pkgforge.dev/pkgforge-cargo/findutils/stable/xargs?tag=0.8.0-aarch64-Linux&manifest",
  "portable": "true",
  "recurse_provides": "false",
  "shasum": "295136cad983acbc886d36e172deea5bf24cb5f28a1d5f413de76e134352d8ad",
  "size": "792 KB",
  "size_raw": "810896",
  "soar_syms": "false",
  "snapshots": [],
  "trusted": "true"
}
