{
  "_disabled": "false",
  "host": "aarch64-Linux",
  "rank": "",
  "pkg": "cargo-watch",
  "pkg_family": "cargo-watch",
  "pkg_id": "pkgforge-cargo.cargo-watch.stable",
  "pkg_name": "cargo-watch",
  "pkg_type": "static",
  "pkg_webpage": "https://crates.io/crates/cargo-watch",
  "bundle": "false",
  "category": [
    "Utility"
  ],
  "description": "Watches over your Cargo project’s source.",
  "homepage": [
    "https://github.com/watchexec/cargo-watch"
  ],
  "license": [
    "CC0-1.0"
  ],
  "maintainer": [
    "pkgforge-cargo (https://github.com/pkgforge-cargo/builder)"
  ],
  "provides": [
    "cargo-watch"
  ],
  "note": [
    "[EXTERNAL] (This is an Official but externally maintained repository)",
    "This package was automatically built from crates.io using cargo-cross",
    "Provided by: https://github.com/pkgforge-cargo/builder",
    "Learn More: https://docs.pkgforge.dev/repositories/external/pkgforge-cargo"
  ],
  "src_url": [
    "https://crates.io/api/v1/crates/cargo-watch/8.5.3/download"
  ],
  "tag": [
    "cargo",
    "compile",
    "notify",
    "watch"
  ],
  "version": "8.5.3",
  "version_upstream": "8.5.3",
  "bsum": "d346bbc71e3be255f6132c94cb49515f0b074a45c236b1202b4433c631221100",
  "build_date": "2025-06-14T19:45:24Z",
  "build_gha": "https://github.com/pkgforge-cargo/builder/actions/runs/15655193944",
  "build_id": "15655193944",
  "build_log": "https://api.ghcr.pkgforge.dev/pkgforge-cargo/cargo-watch/stable/cargo-watch?tag=8.5.3-aarch64-Linux&download=cargo-watch.log",
  "deprecated": "false",
  "desktop_integration": "false",
  "download_count": "106012",
  "download_url": "https://api.ghcr.pkgforge.dev/pkgforge-cargo/cargo-watch/stable/cargo-watch?tag=8.5.3-aarch64-Linux&download=cargo-watch",
  "external": "true",
  "ghcr_pkg": "ghcr.io/pkgforge-cargo/cargo-watch/stable/cargo-watch:8.5.3-aarch64-Linux",
  "ghcr_url": "https://ghcr.io/pkgforge-cargo/cargo-watch/stable/cargo-watch",
  "installable": "true",
  "manifest_url": "https://api.ghcr.pkgforge.dev/pkgforge-cargo/cargo-watch/stable/cargo-watch?tag=8.5.3-aarch64-Linux&manifest",
  "portable": "true",
  "recurse_provides": "false",
  "shasum": "a84d7ab98a07ded2b11ebf2ed5b81c1716a04fe6f2a61ca6e851580b9729b238",
  "size": "4.3 MB",
  "size_raw": "4407544",
  "soar_syms": "false",
  "snapshots": [],
  "trusted": "true"
}
