{
  "_disabled": "false",
  "host": "loongarch64-Linux",
  "rank": "",
  "pkg": "stylua",
  "pkg_family": "stylua",
  "pkg_id": "pkgforge-cargo.stylua.stable",
  "pkg_name": "stylua",
  "pkg_type": "static",
  "pkg_webpage": "https://crates.io/crates/stylua",
  "bundle": "false",
  "category": [
    "Utility"
  ],
  "description": "A code formatter for Lua.",
  "homepage": [
    "https://github.com/johnnymorganz/stylua"
  ],
  "license": [
    "MPL-2.0"
  ],
  "maintainer": [
    "pkgforge-cargo (https://github.com/pkgforge-cargo/builder)"
  ],
  "provides": [
    "stylua"
  ],
  "note": [
    "[EXTERNAL] (This is an Official but externally maintained repository)",
    "This package was automatically built from crates.io using cargo-cross",
    "Provided by: https://github.com/pkgforge-cargo/builder",
    "Learn More: https://docs.pkgforge.dev/repositories/external/pkgforge-cargo"
  ],
  "src_url": [
    "https://crates.io/api/v1/crates/stylua/2.1.0/download"
  ],
  "tag": [
    "cli",
    "formatter",
    "lua",
    "lua51",
    "utility"
  ],
  "version": "2.1.0",
  "version_upstream": "2.1.0",
  "bsum": "5b973991af8f91981cf6c0a975934f02100efa3d5e099a2b8c3b34a724f309bd",
  "build_date": "2025-06-14T21:20:26Z",
  "build_gha": "https://github.com/pkgforge-cargo/builder/actions/runs/15655808718",
  "build_id": "15655808718",
  "build_log": "https://api.ghcr.pkgforge.dev/pkgforge-cargo/stylua/stable/stylua?tag=2.1.0-loongarch64-Linux&download=stylua.log",
  "deprecated": "false",
  "desktop_integration": "false",
  "download_count": "39921",
  "download_url": "https://api.ghcr.pkgforge.dev/pkgforge-cargo/stylua/stable/stylua?tag=2.1.0-loongarch64-Linux&download=stylua",
  "external": "true",
  "ghcr_pkg": "ghcr.io/pkgforge-cargo/stylua/stable/stylua:2.1.0-loongarch64-Linux",
  "ghcr_url": "https://ghcr.io/pkgforge-cargo/stylua/stable/stylua",
  "installable": "true",
  "manifest_url": "https://api.ghcr.pkgforge.dev/pkgforge-cargo/stylua/stable/stylua?tag=2.1.0-loongarch64-Linux&manifest",
  "portable": "true",
  "recurse_provides": "false",
  "shasum": "e0a9c6be2d129feda0a0b5b2df10ec54ac7b46193a1ada58ae6c730f299b0341",
  "size": "5.6 MB",
  "size_raw": "5771224",
  "soar_syms": "false",
  "snapshots": [],
  "trusted": "true"
}
