{
  "_disabled": "false",
  "host": "riscv64-Linux",
  "rank": "",
  "pkg": "cargo-set-version",
  "pkg_family": "cargo-edit",
  "pkg_id": "pkgforge-cargo.cargo-edit.stable",
  "pkg_name": "cargo-set-version",
  "pkg_type": "static",
  "pkg_webpage": "https://crates.io/crates/cargo-edit",
  "bundle": "false",
  "category": [
    "Utility"
  ],
  "description": "Cargo commands for modifying a Cargo.",
  "homepage": [
    "https://github.com/killercup/cargo-edit"
  ],
  "license": [
    "Apache-2.0 OR MIT"
  ],
  "maintainer": [
    "pkgforge-cargo (https://github.com/pkgforge-cargo/builder)"
  ],
  "provides": [
    "cargo-add",
    "cargo-rm",
    "cargo-set-version",
    "cargo-upgrade"
  ],
  "note": [
    "[EXTERNAL] (This is an Official but externally maintained repository)",
    "This package was automatically built from crates.io using cargo-cross",
    "Provided by: https://github.com/pkgforge-cargo/builder",
    "Learn More: https://docs.pkgforge.dev/repositories/external/pkgforge-cargo"
  ],
  "src_url": "https://crates.io/api/v1/crates/cargo-edit/0.13.6/download",
  "tag": [
    "cargo",
    "cargo-subcommand",
    "cli",
    "crates",
    "dependencies"
  ],
  "version": "0.13.6",
  "version_upstream": "0.13.6",
  "bsum": "a812ea5c7974b4bcc6efbcf29fb83fa83a1975af334983859d0ba24adaa67053",
  "build_date": "2025-06-14T11:44:12Z",
  "build_gha": "https://github.com/pkgforge-cargo/builder/actions/runs/15651501024",
  "build_id": "15651501024",
  "build_log": "https://api.ghcr.pkgforge.dev/pkgforge-cargo/cargo-edit/stable/cargo-set-version?tag=0.13.6-riscv64-Linux&download=cargo-set-version.log",
  "deprecated": "false",
  "desktop_integration": "false",
  "download_count": "283508",
  "download_url": "https://api.ghcr.pkgforge.dev/pkgforge-cargo/cargo-edit/stable/cargo-set-version?tag=0.13.6-riscv64-Linux&download=cargo-set-version",
  "external": "true",
  "ghcr_pkg": "ghcr.io/pkgforge-cargo/cargo-edit/stable/cargo-set-version:0.13.6-riscv64-Linux",
  "ghcr_url": "https://ghcr.io/pkgforge-cargo/cargo-edit/stable/cargo-set-version",
  "installable": "true",
  "manifest_url": "https://api.ghcr.pkgforge.dev/pkgforge-cargo/cargo-edit/stable/cargo-set-version?tag=0.13.6-riscv64-Linux&manifest",
  "portable": "true",
  "recurse_provides": "false",
  "shasum": "767d4801c13c3594f610ae40b33f5deea11497b286e86aa623b5d70b45cfe424",
  "size": "2.1 MB",
  "size_raw": "2109448",
  "soar_syms": "false",
  "snapshots": [],
  "trusted": "true"
}
