{
  "_disabled": "false",
  "host": "riscv64-Linux",
  "rank": "",
  "pkg": "audio-mixer",
  "pkg_family": "audio-mixer",
  "pkg_id": "pkgforge-cargo.audio-mixer.stable",
  "pkg_name": "audio-mixer",
  "pkg_type": "static",
  "pkg_webpage": "https://crates.io/crates/audio-mixer",
  "bundle": "false",
  "category": [
    "Utility"
  ],
  "description": "Mixing audio by the input and output channel layout.",
  "homepage": [
    "https://github.com/mozilla/audio-mixer"
  ],
  "license": [
    "MPL-2.0"
  ],
  "maintainer": [
    "pkgforge-cargo (https://github.com/pkgforge-cargo/builder)"
  ],
  "provides": [
    "audio-mixer"
  ],
  "note": [
    "[EXTERNAL] (This is an Official but externally maintained repository)",
    "This package was automatically built from crates.io using cargo-cross",
    "Provided by: https://github.com/pkgforge-cargo/builder",
    "Learn More: https://docs.pkgforge.dev/repositories/external/pkgforge-cargo"
  ],
  "src_url": [
    "https://crates.io/api/v1/crates/audio-mixer/0.2.0/download"
  ],
  "tag": [
    "audio",
    "mixer",
    "mixing"
  ],
  "version": "0.2.0",
  "version_upstream": "0.2.0",
  "bsum": "8f6ba8ff7b21f34a5060e3ed3b106bc840944f4c10afbc0a921871d08aa6806a",
  "build_date": "2025-06-15T17:27:01Z",
  "build_gha": "https://github.com/pkgforge-cargo/builder/actions/runs/15665341559",
  "build_id": "15665341559",
  "build_log": "https://api.ghcr.pkgforge.dev/pkgforge-cargo/audio-mixer/stable/audio-mixer?tag=0.2.0-riscv64-Linux&download=audio-mixer.log",
  "deprecated": "false",
  "desktop_integration": "false",
  "download_count": "4402",
  "download_url": "https://api.ghcr.pkgforge.dev/pkgforge-cargo/audio-mixer/stable/audio-mixer?tag=0.2.0-riscv64-Linux&download=audio-mixer",
  "external": "true",
  "ghcr_pkg": "ghcr.io/pkgforge-cargo/audio-mixer/stable/audio-mixer:0.2.0-riscv64-Linux",
  "ghcr_url": "https://ghcr.io/pkgforge-cargo/audio-mixer/stable/audio-mixer",
  "installable": "true",
  "manifest_url": "https://api.ghcr.pkgforge.dev/pkgforge-cargo/audio-mixer/stable/audio-mixer?tag=0.2.0-riscv64-Linux&manifest",
  "portable": "true",
  "recurse_provides": "false",
  "shasum": "4c3bbb136456878e68ae8ef97cd2c98e9744c12b83ac6d8f91df4a494e7bd49f",
  "size": "384 KB",
  "size_raw": "393160",
  "soar_syms": "false",
  "snapshots": [],
  "trusted": "true"
}
