{
  "_disabled": "false",
  "host": "aarch64-Linux",
  "rank": "",
  "pkg": "az65",
  "pkg_family": "az65",
  "pkg_id": "pkgforge-cargo.az65.stable",
  "pkg_name": "az65",
  "pkg_type": "static",
  "pkg_webpage": "https://crates.io/crates/az65",
  "bundle": "false",
  "category": [
    "Utility"
  ],
  "description": "A multi-CPU assembler.",
  "homepage": [
    "https://github.com/lavignes/az65"
  ],
  "license": [
    "Apache-2.0"
  ],
  "maintainer": [
    "pkgforge-cargo (https://github.com/pkgforge-cargo/builder)"
  ],
  "provides": [
    "az65"
  ],
  "note": [
    "[EXTERNAL] (This is an Official but externally maintained repository)",
    "This package was automatically built from crates.io using cargo-cross",
    "Provided by: https://github.com/pkgforge-cargo/builder",
    "Learn More: https://docs.pkgforge.dev/repositories/external/pkgforge-cargo"
  ],
  "src_url": [
    "https://crates.io/api/v1/crates/az65/0.1.11/download"
  ],
  "tag": [
    "Utility"
  ],
  "version": "0.1.11",
  "version_upstream": "0.1.11",
  "bsum": "20b2620cbc33a827688b864f1d194b074fdf0e55b0832a0ed25f693ed25eef26",
  "build_date": "2025-06-15T19:41:28Z",
  "build_gha": "https://github.com/pkgforge-cargo/builder/actions/runs/15666304884",
  "build_id": "15666304884",
  "build_log": "https://api.ghcr.pkgforge.dev/pkgforge-cargo/az65/stable/az65?tag=0.1.11-aarch64-Linux&download=az65.log",
  "deprecated": "false",
  "desktop_integration": "false",
  "download_count": "1941",
  "download_url": "https://api.ghcr.pkgforge.dev/pkgforge-cargo/az65/stable/az65?tag=0.1.11-aarch64-Linux&download=az65",
  "external": "true",
  "ghcr_pkg": "ghcr.io/pkgforge-cargo/az65/stable/az65:0.1.11-aarch64-Linux",
  "ghcr_url": "https://ghcr.io/pkgforge-cargo/az65/stable/az65",
  "installable": "true",
  "manifest_url": "https://api.ghcr.pkgforge.dev/pkgforge-cargo/az65/stable/az65?tag=0.1.11-aarch64-Linux&manifest",
  "portable": "true",
  "recurse_provides": "false",
  "shasum": "16f7f971fb17907adbee6d59cb343956d0fab12f6606eb1e0f7294e28d7fe096",
  "size": "1.5 MB",
  "size_raw": "1519632",
  "soar_syms": "false",
  "snapshots": [],
  "trusted": "true"
}
