{
  "_disabled": "false",
  "host": "aarch64-Linux",
  "rank": "",
  "pkg": "gateway",
  "pkg_family": "agp-gw",
  "pkg_id": "pkgforge-cargo.agp-gw.stable",
  "pkg_name": "gateway",
  "pkg_type": "static",
  "pkg_webpage": "https://crates.io/crates/agp-gw",
  "bundle": "false",
  "category": [
    "Utility"
  ],
  "description": "The main gateway executable.",
  "homepage": [
    "https://crates.io/crates/agp-gw"
  ],
  "license": [
    "Apache-2.0"
  ],
  "maintainer": [
    "pkgforge-cargo (https://github.com/pkgforge-cargo/builder)"
  ],
  "provides": [
    "gateway"
  ],
  "note": [
    "[EXTERNAL] (This is an Official but externally maintained repository)",
    "This package was automatically built from crates.io using cargo-cross",
    "Provided by: https://github.com/pkgforge-cargo/builder",
    "Learn More: https://docs.pkgforge.dev/repositories/external/pkgforge-cargo"
  ],
  "src_url": [
    "https://crates.io/api/v1/crates/agp-gw/0.3.15/download"
  ],
  "tag": [
    "Utility"
  ],
  "version": "0.3.15",
  "version_upstream": "0.3.15",
  "bsum": "dae8efb3f4920211f7e6aa388a82e1e690a2ed1e45b97763e8cee4a556d45fce",
  "build_date": "2025-06-15T10:16:16Z",
  "build_gha": "https://github.com/pkgforge-cargo/builder/actions/runs/15661954010",
  "build_id": "15661954010",
  "build_log": "https://api.ghcr.pkgforge.dev/pkgforge-cargo/agp-gw/stable/gateway?tag=0.3.15-aarch64-Linux&download=gateway.log",
  "deprecated": "false",
  "desktop_integration": "false",
  "download_count": "5571",
  "download_url": "https://api.ghcr.pkgforge.dev/pkgforge-cargo/agp-gw/stable/gateway?tag=0.3.15-aarch64-Linux&download=gateway",
  "external": "true",
  "ghcr_pkg": "ghcr.io/pkgforge-cargo/agp-gw/stable/gateway:0.3.15-aarch64-Linux",
  "ghcr_url": "https://ghcr.io/pkgforge-cargo/agp-gw/stable/gateway",
  "installable": "true",
  "manifest_url": "https://api.ghcr.pkgforge.dev/pkgforge-cargo/agp-gw/stable/gateway?tag=0.3.15-aarch64-Linux&manifest",
  "portable": "true",
  "recurse_provides": "false",
  "shasum": "d4ac245b7c5e9ad998454da79ccc561bfcc12f60133e4dc994a357f9d18bae7d",
  "size": "9.4 MB",
  "size_raw": "9808896",
  "soar_syms": "false",
  "snapshots": [],
  "trusted": "true"
}
