{
  "_disabled": "false",
  "host": "x86_64-Linux",
  "rank": "",
  "pkg": "serpl",
  "pkg_family": "serpl",
  "pkg_id": "pkgforge-cargo.serpl.stable",
  "pkg_name": "serpl",
  "pkg_type": "static",
  "pkg_webpage": "https://crates.io/crates/serpl",
  "bundle": "false",
  "category": [
    "Utility"
  ],
  "description": "A simple terminal UI for search and replace, ala VS Code.",
  "homepage": [
    "https://github.com/yassinebridi/serpl"
  ],
  "license": [
    "MIT"
  ],
  "maintainer": [
    "pkgforge-cargo (https://github.com/pkgforge-cargo/builder)"
  ],
  "provides": [
    "serpl"
  ],
  "note": [
    "[EXTERNAL] (This is an Official but externally maintained repository)",
    "This package was automatically built from crates.io using cargo-cross",
    "Provided by: https://github.com/pkgforge-cargo/builder",
    "Learn More: https://docs.pkgforge.dev/repositories/external/pkgforge-cargo"
  ],
  "src_url": [
    "https://crates.io/api/v1/crates/serpl/0.3.4/download"
  ],
  "tag": [
    "Utility"
  ],
  "version": "0.3.4",
  "version_upstream": "0.3.4",
  "bsum": "361668fda0ef67ef1df78ef521e0e1f4b2e1164ec66af3c51c2be1c1bdbe6038",
  "build_date": "2025-06-15T01:21:52Z",
  "build_gha": "https://github.com/pkgforge-cargo/builder/actions/runs/15657526826",
  "build_id": "15657526826",
  "build_log": "https://api.ghcr.pkgforge.dev/pkgforge-cargo/serpl/stable/serpl?tag=0.3.4-x86_64-Linux&download=serpl.log",
  "deprecated": "false",
  "desktop_integration": "false",
  "download_count": "4252",
  "download_url": "https://api.ghcr.pkgforge.dev/pkgforge-cargo/serpl/stable/serpl?tag=0.3.4-x86_64-Linux&download=serpl",
  "external": "true",
  "ghcr_pkg": "ghcr.io/pkgforge-cargo/serpl/stable/serpl:0.3.4-x86_64-Linux",
  "ghcr_url": "https://ghcr.io/pkgforge-cargo/serpl/stable/serpl",
  "installable": "true",
  "manifest_url": "https://api.ghcr.pkgforge.dev/pkgforge-cargo/serpl/stable/serpl?tag=0.3.4-x86_64-Linux&manifest",
  "portable": "true",
  "recurse_provides": "false",
  "shasum": "db29e3a09634ea9b6a1314aa77b3873de9d92e0eb1398b5d3efbb19f37b86fa1",
  "size": "5.2 MB",
  "size_raw": "5409944",
  "soar_syms": "false",
  "snapshots": [],
  "trusted": "true"
}
