{
  "_disabled": "false",
  "host": "x86_64-Linux",
  "rank": "",
  "pkg": "avm1-tree",
  "pkg_family": "avm1-tree",
  "pkg_id": "pkgforge-cargo.avm1-tree.stable",
  "pkg_name": "avm1-tree",
  "pkg_type": "static",
  "pkg_webpage": "https://crates.io/crates/avm1-tree",
  "bundle": "false",
  "category": [
    "Utility"
  ],
  "description": "Abstract Syntax Tree (AST) for AVM1.",
  "homepage": [
    "https://github.com/open-flash/avm1-tree"
  ],
  "license": [
    "MIT/Apache-2.0"
  ],
  "maintainer": [
    "pkgforge-cargo (https://github.com/pkgforge-cargo/builder)"
  ],
  "provides": [
    "avm1-tree"
  ],
  "note": [
    "[EXTERNAL] (This is an Official but externally maintained repository)",
    "This package was automatically built from crates.io using cargo-cross",
    "Provided by: https://github.com/pkgforge-cargo/builder",
    "Learn More: https://docs.pkgforge.dev/repositories/external/pkgforge-cargo"
  ],
  "src_url": [
    "https://crates.io/api/v1/crates/avm1-tree/0.8.0/download"
  ],
  "tag": [
    "ast",
    "avm1",
    "swf"
  ],
  "version": "0.8.0",
  "version_upstream": "0.8.0",
  "bsum": "e60d977a4597e096e7e5bf68b0cc32e95bf12bd580ff0254fdd4821b17b1d98f",
  "build_date": "2025-06-15T18:55:47Z",
  "build_gha": "https://github.com/pkgforge-cargo/builder/actions/runs/15666216563",
  "build_id": "15666216563",
  "build_log": "https://api.ghcr.pkgforge.dev/pkgforge-cargo/avm1-tree/stable/avm1-tree?tag=0.8.0-x86_64-Linux&download=avm1-tree.log",
  "deprecated": "false",
  "desktop_integration": "false",
  "download_count": "1691",
  "download_url": "https://api.ghcr.pkgforge.dev/pkgforge-cargo/avm1-tree/stable/avm1-tree?tag=0.8.0-x86_64-Linux&download=avm1-tree",
  "external": "true",
  "ghcr_pkg": "ghcr.io/pkgforge-cargo/avm1-tree/stable/avm1-tree:0.8.0-x86_64-Linux",
  "ghcr_url": "https://ghcr.io/pkgforge-cargo/avm1-tree/stable/avm1-tree",
  "installable": "true",
  "manifest_url": "https://api.ghcr.pkgforge.dev/pkgforge-cargo/avm1-tree/stable/avm1-tree?tag=0.8.0-x86_64-Linux&manifest",
  "portable": "true",
  "recurse_provides": "false",
  "shasum": "22fa5a160c8f883511b7099b0d2c3442afe564edb525037b8aa17d61ef379f90",
  "size": "649 KB",
  "size_raw": "664008",
  "soar_syms": "false",
  "snapshots": [],
  "trusted": "true"
}
