{
  "_disabled": "false",
  "host": "loongarch64-Linux",
  "rank": "",
  "pkg": "main",
  "pkg_family": "abstract-calculus",
  "pkg_id": "pkgforge-cargo.abstract-calculus.stable",
  "pkg_name": "main",
  "pkg_type": "static",
  "pkg_webpage": "https://crates.io/crates/abstract-calculus",
  "bundle": "false",
  "category": [
    "Utility"
  ],
  "description": "A programming language and model of computation that matches the abstract algorithm perfectly.",
  "homepage": [
    "https://github.com/maiavictor/abstract-calculus"
  ],
  "license": [
    "MIT"
  ],
  "maintainer": [
    "pkgforge-cargo (https://github.com/pkgforge-cargo/builder)"
  ],
  "provides": [
    "main"
  ],
  "note": [
    "[EXTERNAL] (This is an Official but externally maintained repository)",
    "This package was automatically built from crates.io using cargo-cross",
    "Provided by: https://github.com/pkgforge-cargo/builder",
    "Learn More: https://docs.pkgforge.dev/repositories/external/pkgforge-cargo"
  ],
  "src_url": [
    "https://crates.io/api/v1/crates/abstract-calculus/0.1.5/download"
  ],
  "tag": [
    "Utility"
  ],
  "version": "0.1.5",
  "version_upstream": "0.1.5",
  "bsum": "e76b49ea400c5ddb611b61c0b4175c84e53d6d1de47aba513a239a11990bea80",
  "build_date": "2025-06-15T03:52:07Z",
  "build_gha": "https://github.com/pkgforge-cargo/builder/actions/runs/15658855448",
  "build_id": "15658855448",
  "build_log": "https://api.ghcr.pkgforge.dev/pkgforge-cargo/abstract-calculus/stable/main?tag=0.1.5-loongarch64-Linux&download=main.log",
  "deprecated": "false",
  "desktop_integration": "false",
  "download_count": "1206",
  "download_url": "https://api.ghcr.pkgforge.dev/pkgforge-cargo/abstract-calculus/stable/main?tag=0.1.5-loongarch64-Linux&download=main",
  "external": "true",
  "ghcr_pkg": "ghcr.io/pkgforge-cargo/abstract-calculus/stable/main:0.1.5-loongarch64-Linux",
  "ghcr_url": "https://ghcr.io/pkgforge-cargo/abstract-calculus/stable/main",
  "installable": "true",
  "manifest_url": "https://api.ghcr.pkgforge.dev/pkgforge-cargo/abstract-calculus/stable/main?tag=0.1.5-loongarch64-Linux&manifest",
  "portable": "true",
  "recurse_provides": "false",
  "shasum": "bcbad2a8ffee1d913380aa46d01d8edcb5293f89cfc10aeaf1b34f9751d8a316",
  "size": "468 KB",
  "size_raw": "478992",
  "soar_syms": "false",
  "snapshots": [],
  "trusted": "true"
}
