{
  "_disabled": "false",
  "host": "x86_64-Linux",
  "rank": "",
  "pkg": "aether",
  "pkg_family": "aether",
  "pkg_id": "pkgforge-cargo.aether.stable",
  "pkg_name": "aether",
  "pkg_type": "static",
  "pkg_webpage": "https://crates.io/crates/aether",
  "bundle": "false",
  "category": [
    "Utility"
  ],
  "description": "a native web assembly programming language.",
  "homepage": [
    "https://crates.io/crates/aether"
  ],
  "license": [
    "MIT"
  ],
  "maintainer": [
    "pkgforge-cargo (https://github.com/pkgforge-cargo/builder)"
  ],
  "provides": [
    "aether"
  ],
  "note": [
    "[EXTERNAL] (This is an Official but externally maintained repository)",
    "This package was automatically built from crates.io using cargo-cross",
    "Provided by: https://github.com/pkgforge-cargo/builder",
    "Learn More: https://docs.pkgforge.dev/repositories/external/pkgforge-cargo"
  ],
  "src_url": [
    "https://crates.io/api/v1/crates/aether/0.0.3/download"
  ],
  "tag": [
    "Utility"
  ],
  "version": "0.0.3",
  "version_upstream": "0.0.3",
  "bsum": "909677f1f785f4a734df115e83872fb0fdc45ad1d682fc4fe99d8e88b1812fb5",
  "build_date": "2025-06-15T05:03:40Z",
  "build_gha": "https://github.com/pkgforge-cargo/builder/actions/runs/15659490905",
  "build_id": "15659490905",
  "build_log": "https://api.ghcr.pkgforge.dev/pkgforge-cargo/aether/stable/aether?tag=0.0.3-x86_64-Linux&download=aether.log",
  "deprecated": "false",
  "desktop_integration": "false",
  "download_count": "569",
  "download_url": "https://api.ghcr.pkgforge.dev/pkgforge-cargo/aether/stable/aether?tag=0.0.3-x86_64-Linux&download=aether",
  "external": "true",
  "ghcr_pkg": "ghcr.io/pkgforge-cargo/aether/stable/aether:0.0.3-x86_64-Linux",
  "ghcr_url": "https://ghcr.io/pkgforge-cargo/aether/stable/aether",
  "installable": "true",
  "manifest_url": "https://api.ghcr.pkgforge.dev/pkgforge-cargo/aether/stable/aether?tag=0.0.3-x86_64-Linux&manifest",
  "portable": "true",
  "recurse_provides": "false",
  "shasum": "e2144c7007f4d5f6d22099c9dad02abe72a9e647037a4a94c6b195ebca652b52",
  "size": "625 KB",
  "size_raw": "639432",
  "soar_syms": "false",
  "snapshots": [],
  "trusted": "true"
}
