{
  "_disabled": "false",
  "host": "riscv64-Linux",
  "rank": "",
  "pkg": "ask",
  "pkg_family": "ask-cli",
  "pkg_id": "pkgforge-cargo.ask-cli.stable",
  "pkg_name": "ask",
  "pkg_type": "static",
  "pkg_webpage": "https://crates.io/crates/ask-cli",
  "bundle": "false",
  "category": [
    "Utility"
  ],
  "description": "Ask CLI offers a simple way to ask a yes or no question.",
  "homepage": [
    "https://github.com/SUPERCILEX/ask-cli"
  ],
  "license": [
    "Apache-2.0"
  ],
  "maintainer": [
    "pkgforge-cargo (https://github.com/pkgforge-cargo/builder)"
  ],
  "provides": [
    "ask"
  ],
  "note": [
    "[EXTERNAL] (This is an Official but externally maintained repository)",
    "This package was automatically built from crates.io using cargo-cross",
    "Provided by: https://github.com/pkgforge-cargo/builder",
    "Learn More: https://docs.pkgforge.dev/repositories/external/pkgforge-cargo"
  ],
  "src_url": [
    "https://crates.io/api/v1/crates/ask-cli/0.3.0/download"
  ],
  "tag": [
    "answer",
    "ask",
    "cli",
    "prompt",
    "question"
  ],
  "version": "0.3.0",
  "version_upstream": "0.3.0",
  "bsum": "d88b32c222eaba546f35fdddbacf46ff4b1b3f48236bcbd65fd2d846621ed494",
  "build_date": "2025-06-15T16:19:47Z",
  "build_gha": "https://github.com/pkgforge-cargo/builder/actions/runs/15664785528",
  "build_id": "15664785528",
  "build_log": "https://api.ghcr.pkgforge.dev/pkgforge-cargo/ask-cli/stable/ask?tag=0.3.0-riscv64-Linux&download=ask.log",
  "deprecated": "false",
  "desktop_integration": "false",
  "download_count": "2142",
  "download_url": "https://api.ghcr.pkgforge.dev/pkgforge-cargo/ask-cli/stable/ask?tag=0.3.0-riscv64-Linux&download=ask",
  "external": "true",
  "ghcr_pkg": "ghcr.io/pkgforge-cargo/ask-cli/stable/ask:0.3.0-riscv64-Linux",
  "ghcr_url": "https://ghcr.io/pkgforge-cargo/ask-cli/stable/ask",
  "installable": "true",
  "manifest_url": "https://api.ghcr.pkgforge.dev/pkgforge-cargo/ask-cli/stable/ask?tag=0.3.0-riscv64-Linux&manifest",
  "portable": "true",
  "recurse_provides": "false",
  "shasum": "a90a9a97e7992b8a538eb3143cae00d67d0a659d67e124861f5cfe070ade8fbb",
  "size": "368 KB",
  "size_raw": "376776",
  "soar_syms": "false",
  "snapshots": [],
  "trusted": "true"
}
