{
  "_disabled": "false",
  "host": "x86_64-Linux",
  "rank": "",
  "pkg": "wr",
  "pkg_family": "workshop-runner",
  "pkg_id": "pkgforge-cargo.workshop-runner.stable",
  "pkg_name": "wr",
  "pkg_type": "static",
  "pkg_webpage": "https://crates.io/crates/workshop-runner",
  "bundle": "false",
  "category": [
    "Utility"
  ],
  "description": "A CLI to run test-driven Rust workshops.",
  "homepage": [
    "https://github.com/mainmatter/rust-workshop-runner"
  ],
  "license": [
    "Apache-2.0 OR MIT"
  ],
  "maintainer": [
    "pkgforge-cargo (https://github.com/pkgforge-cargo/builder)"
  ],
  "provides": [
    "wr"
  ],
  "note": [
    "[EXTERNAL] (This is an Official but externally maintained repository)",
    "This package was automatically built from crates.io using cargo-cross",
    "Provided by: https://github.com/pkgforge-cargo/builder",
    "Learn More: https://docs.pkgforge.dev/repositories/external/pkgforge-cargo"
  ],
  "src_url": [
    "https://crates.io/api/v1/crates/workshop-runner/0.2.4/download"
  ],
  "tag": [
    "education",
    "learning",
    "workshop"
  ],
  "version": "0.2.4",
  "version_upstream": "0.2.4",
  "bsum": "7c52f33c4d5f415a20a91ff7c3652cde031f7364ee97686314624fcac710bb11",
  "build_date": "2025-06-15T02:16:09Z",
  "build_gha": "https://github.com/pkgforge-cargo/builder/actions/runs/15658033023",
  "build_id": "15658033023",
  "build_log": "https://api.ghcr.pkgforge.dev/pkgforge-cargo/workshop-runner/stable/wr?tag=0.2.4-x86_64-Linux&download=wr.log",
  "deprecated": "false",
  "desktop_integration": "false",
  "download_count": "3087",
  "download_url": "https://api.ghcr.pkgforge.dev/pkgforge-cargo/workshop-runner/stable/wr?tag=0.2.4-x86_64-Linux&download=wr",
  "external": "true",
  "ghcr_pkg": "ghcr.io/pkgforge-cargo/workshop-runner/stable/wr:0.2.4-x86_64-Linux",
  "ghcr_url": "https://ghcr.io/pkgforge-cargo/workshop-runner/stable/wr",
  "installable": "true",
  "manifest_url": "https://api.ghcr.pkgforge.dev/pkgforge-cargo/workshop-runner/stable/wr?tag=0.2.4-x86_64-Linux&manifest",
  "portable": "true",
  "recurse_provides": "false",
  "shasum": "73228d3c9d420d015b7f4da76752ee16703fc7a3ad66eca6d7098278416874e2",
  "size": "4.6 MB",
  "size_raw": "4723624",
  "soar_syms": "false",
  "snapshots": [],
  "trusted": "true"
}
