{
  "_disabled": "false",
  "host": "x86_64-Linux",
  "rank": "",
  "pkg": "ashpaper",
  "pkg_family": "ashpaper-bin",
  "pkg_id": "pkgforge-cargo.ashpaper-bin.stable",
  "pkg_name": "ashpaper",
  "pkg_type": "static",
  "pkg_webpage": "https://crates.io/crates/ashpaper-bin",
  "bundle": "false",
  "category": [
    "Utility"
  ],
  "description": "CLI for ashpaper, an inpterpreter for Esopo language AshPaper conceived by William Hicks.",
  "homepage": [
    "https://github.com/shnewto/ashpaper"
  ],
  "license": [
    "MIT"
  ],
  "maintainer": [
    "pkgforge-cargo (https://github.com/pkgforge-cargo/builder)"
  ],
  "provides": [
    "ashpaper"
  ],
  "note": [
    "[EXTERNAL] (This is an Official but externally maintained repository)",
    "This package was automatically built from crates.io using cargo-cross",
    "Provided by: https://github.com/pkgforge-cargo/builder",
    "Learn More: https://docs.pkgforge.dev/repositories/external/pkgforge-cargo"
  ],
  "src_url": [
    "https://crates.io/api/v1/crates/ashpaper-bin/0.2.1/download"
  ],
  "tag": [
    "cli",
    "esolang",
    "esopo",
    "interpreter",
    "poetry"
  ],
  "version": "0.2.1",
  "version_upstream": "0.2.1",
  "bsum": "a4117ad638b4edef378c7de1d7759adc6f515f57b268c7860c1e8ee755aa6cad",
  "build_date": "2025-06-15T16:13:17Z",
  "build_gha": "https://github.com/pkgforge-cargo/builder/actions/runs/15664776620",
  "build_id": "15664776620",
  "build_log": "https://api.ghcr.pkgforge.dev/pkgforge-cargo/ashpaper-bin/stable/ashpaper?tag=0.2.1-x86_64-Linux&download=ashpaper.log",
  "deprecated": "false",
  "desktop_integration": "false",
  "download_count": "1226",
  "download_url": "https://api.ghcr.pkgforge.dev/pkgforge-cargo/ashpaper-bin/stable/ashpaper?tag=0.2.1-x86_64-Linux&download=ashpaper",
  "external": "true",
  "ghcr_pkg": "ghcr.io/pkgforge-cargo/ashpaper-bin/stable/ashpaper:0.2.1-x86_64-Linux",
  "ghcr_url": "https://ghcr.io/pkgforge-cargo/ashpaper-bin/stable/ashpaper",
  "installable": "true",
  "manifest_url": "https://api.ghcr.pkgforge.dev/pkgforge-cargo/ashpaper-bin/stable/ashpaper?tag=0.2.1-x86_64-Linux&manifest",
  "portable": "true",
  "recurse_provides": "false",
  "shasum": "1e7e35cfced3fad8c6b58bd7f2b876a57272c5ad3a3fac2d4348a58abfbf0c93",
  "size": "2.0 MB",
  "size_raw": "2003536",
  "soar_syms": "false",
  "snapshots": [],
  "trusted": "true"
}
