{
  "_disabled": "false",
  "host": "loongarch64-Linux",
  "rank": "",
  "pkg": "bingo",
  "pkg_family": "bingogo",
  "pkg_id": "pkgforge-cargo.bingogo.stable",
  "pkg_name": "bingo",
  "pkg_type": "static",
  "pkg_webpage": "https://crates.io/crates/bingogo",
  "bundle": "false",
  "category": [
    "Utility"
  ],
  "description": "An executable file manager written in Rust.",
  "homepage": [
    "https://github.com/dwpeng/bingo"
  ],
  "license": [
    "MIT"
  ],
  "maintainer": [
    "pkgforge-cargo (https://github.com/pkgforge-cargo/builder)"
  ],
  "provides": [
    "bingo"
  ],
  "note": [
    "[EXTERNAL] (This is an Official but externally maintained repository)",
    "This package was automatically built from crates.io using cargo-cross",
    "Provided by: https://github.com/pkgforge-cargo/builder",
    "Learn More: https://docs.pkgforge.dev/repositories/external/pkgforge-cargo"
  ],
  "src_url": [
    "https://crates.io/api/v1/crates/bingogo/0.2.1/download"
  ],
  "tag": [
    "Utility"
  ],
  "version": "0.2.1",
  "version_upstream": "0.2.1",
  "bsum": "26bc987221bf4c59d147f93e1372dc17f0fe77d4717279c064b443302fb09597",
  "build_date": "2025-06-15T23:19:39Z",
  "build_gha": "https://github.com/pkgforge-cargo/builder/actions/runs/15668108994",
  "build_id": "15668108994",
  "build_log": "https://api.ghcr.pkgforge.dev/pkgforge-cargo/bingogo/stable/bingo?tag=0.2.1-loongarch64-Linux&download=bingo.log",
  "deprecated": "false",
  "desktop_integration": "false",
  "download_count": "736",
  "download_url": "https://api.ghcr.pkgforge.dev/pkgforge-cargo/bingogo/stable/bingo?tag=0.2.1-loongarch64-Linux&download=bingo",
  "external": "true",
  "ghcr_pkg": "ghcr.io/pkgforge-cargo/bingogo/stable/bingo:0.2.1-loongarch64-Linux",
  "ghcr_url": "https://ghcr.io/pkgforge-cargo/bingogo/stable/bingo",
  "installable": "true",
  "manifest_url": "https://api.ghcr.pkgforge.dev/pkgforge-cargo/bingogo/stable/bingo?tag=0.2.1-loongarch64-Linux&manifest",
  "portable": "true",
  "recurse_provides": "false",
  "shasum": "aadb2dedc4f1dc03c8cbd10f4043ef986c4d8bae21f9136481a53bab33554ff7",
  "size": "964 KB",
  "size_raw": "986904",
  "soar_syms": "false",
  "snapshots": [],
  "trusted": "true"
}
