{
  "_disabled": "false",
  "host": "aarch64-Linux",
  "rank": "",
  "pkg": "aocoracle",
  "pkg_family": "aocoracle",
  "pkg_id": "pkgforge-cargo.aocoracle.stable",
  "pkg_name": "aocoracle",
  "pkg_type": "static",
  "pkg_webpage": "https://crates.io/crates/aocoracle",
  "bundle": "false",
  "category": [
    "Utility"
  ],
  "description": "Universal solver for advent of code problems.",
  "homepage": [
    "https://crates.io/crates/aocoracle"
  ],
  "license": [
    "MIT"
  ],
  "maintainer": [
    "pkgforge-cargo (https://github.com/pkgforge-cargo/builder)"
  ],
  "provides": [
    "aocoracle"
  ],
  "note": [
    "[EXTERNAL] (This is an Official but externally maintained repository)",
    "This package was automatically built from crates.io using cargo-cross",
    "Provided by: https://github.com/pkgforge-cargo/builder",
    "Learn More: https://docs.pkgforge.dev/repositories/external/pkgforge-cargo"
  ],
  "src_url": [
    "https://crates.io/api/v1/crates/aocoracle/0.1.2/download"
  ],
  "tag": [
    "Utility"
  ],
  "version": "0.1.2",
  "version_upstream": "0.1.2",
  "bsum": "4a036a45f33fddfa2ccd058c71059a4845119103322ee32ea1a63cef78c7da60",
  "build_date": "2025-06-15T13:43:00Z",
  "build_gha": "https://github.com/pkgforge-cargo/builder/actions/runs/15663434669",
  "build_id": "15663434669",
  "build_log": "https://api.ghcr.pkgforge.dev/pkgforge-cargo/aocoracle/stable/aocoracle?tag=0.1.2-aarch64-Linux&download=aocoracle.log",
  "deprecated": "false",
  "desktop_integration": "false",
  "download_count": "568",
  "download_url": "https://api.ghcr.pkgforge.dev/pkgforge-cargo/aocoracle/stable/aocoracle?tag=0.1.2-aarch64-Linux&download=aocoracle",
  "external": "true",
  "ghcr_pkg": "ghcr.io/pkgforge-cargo/aocoracle/stable/aocoracle:0.1.2-aarch64-Linux",
  "ghcr_url": "https://ghcr.io/pkgforge-cargo/aocoracle/stable/aocoracle",
  "installable": "true",
  "manifest_url": "https://api.ghcr.pkgforge.dev/pkgforge-cargo/aocoracle/stable/aocoracle?tag=0.1.2-aarch64-Linux&manifest",
  "portable": "true",
  "recurse_provides": "false",
  "shasum": "ea58c5a320ac5b3d952fa1b2ff5694ab0175c9e49a8021a24aa26435e06ea96f",
  "size": "1.6 MB",
  "size_raw": "1658888",
  "soar_syms": "false",
  "snapshots": [],
  "trusted": "true"
}
